LICENSE
MANIFEST.in
README.md
dockbot.json
setup.py
dockbot/Config.py
dockbot/Container.py
dockbot/Dockbot.py
dockbot/Error.py
dockbot/Image.py
dockbot/Master.py
dockbot/Slave.py
dockbot/__init__.py
dockbot/github.py
dockbot/publish.py
dockbot/util.py
dockbot.egg-info/PKG-INFO
dockbot.egg-info/SOURCES.txt
dockbot.egg-info/dependency_links.txt
dockbot.egg-info/eager_resources.txt
dockbot.egg-info/entry_points.txt
dockbot.egg-info/requires.txt
dockbot.egg-info/top_level.txt
dockbot/data/slave.tac
dockbot/data/lib/boost-1.59.0.m4
dockbot/data/lib/boost.m4
dockbot/data/lib/buildbot.m4
dockbot/data/lib/centos.m4
dockbot/data/lib/debian.m4
dockbot/data/lib/epel5.m4
dockbot/data/lib/epel6.m4
dockbot/data/lib/gcc-4.8.m4
dockbot/data/lib/gcc-4.9.m4
dockbot/data/lib/gcc.m4
dockbot/data/lib/leveldb.m4
dockbot/data/lib/make.m4
dockbot/data/lib/node.m4
dockbot/data/lib/openssl.m4
dockbot/data/lib/slave.m4
dockbot/data/lib/twisted.m4
dockbot/data/lib/zope.m4
dockbot/data/master/github-hook.py
dockbot/data/master/master.docker
dockbot/data/master/master.py
dockbot/data/master/master.tac
dockbot/data/master/nginx.conf
dockbot/data/master/public_html/buildbot.css
dockbot/data/master/public_html/index.html
dockbot/data/master/public_html/robots.txt
slaves/Debian-Testing-32bit/base.m4
slaves/Debian-Testing-32bit/cbang.docker
slaves/Debian-Testing-32bit/dockbot.json
slaves/Debian-Testing-64bit/base.m4
slaves/Debian-Testing-64bit/cbang.docker
slaves/Debian-Testing-64bit/dockbot.json
slaves/Windows-Cross-64bit/base.m4
slaves/Windows-Cross-64bit/cbang.docker
slaves/Windows-Cross-64bit/dockbot.json