Metadata-Version: 1.0
Name: dockbot
Version: 0.1.5
Summary: A continuous integration system which uses Docker and Buildbot
Home-page: https://github.com/CauldronDevelopmentLLC/dockbot
Author: Joseph Coffland
Author-email: joseph@cauldrondevelopment.com
License: GPL 3+
Platform: any
